blog_app/__init__.py
blog_app/config.py
blog_app/database.py
blog_app/posts.py
blog_app-0.1.3.dist-info/LICENSE
blog_app-0.1.3.dist-info/METADATA
blog_app-0.1.3.dist-info/WHEEL
blog_app-0.1.3.dist-info/entry_points.txt
blog_app-0.1.3.dist-info/top_level.txt
blog_app-0.1.3.dist-info/RECORD
