Metadata-Version: 2.1
Name: blog-app
Version: 0.1.3
Summary: A simple blog application with Flask
Home-page: https://gitlab.com/m.sanvito17/2024_assignment2_blogpss2
Author: Team IT
Author-email: y.karzal@campus.unimib.it
Classifier: Development Status :: 3 - Alpha
Classifier: Programming Language :: Python :: 3
Classifier: Programming Language :: Python :: 3.11
Classifier: License :: OSI Approved :: MIT License
Classifier: Operating System :: OS Independent
Classifier: Framework :: Flask
Requires-Python: >=3.11
License-File: LICENSE
Requires-Dist: flask>=3.1.0
Requires-Dist: flask-sqlalchemy>=3.1.1
Requires-Dist: flask-cors>=5.0.0
Requires-Dist: python-dotenv>=1.0.1
